Metadata-Version: 1.0
Name: number-guesser
Version: 0.1
Summary: The computer makes a guess and you have to get it right
Home-page: UNKNOWN
Author: Lluis Guardia
Author-email: UNKNOWN
License: UNKNOWN
Platform: UNKNOWN
